Workbook

Sheet Summary
A1: WavePalace — Revenue Model Summary (Year 1)
A3: Headline outputs | E3: Year 1 revenue mix by stream
A4: Year 1 total revenue | B4: =Projection!L15 | E4: Revenue stream | F4: Year 1 ($) | G4: % mix
A5: Ending MRR (Month 12, recurring) | B5: =Projection!N14 | E5: Host Pro subscriptions | F5: =Projection!E15 | G5: =F5/$F$12
A6: Ending total monthly revenue (Month 12) | B6: =Projection!L14 | E6: Featured placement | F6: =Projection!F15 | G6: =F6/$F$12
A7: Active hosts (Month 12) | B7: =Projection!B14 | E7: White-label / B2B | F7: =Projection!G15 | G7: =F7/$F$12
A8: Active listeners (Month 12) | B8: =Projection!C14 | E8: Tips (net) | F8: =Projection!H15 | G8: =F8/$F$12
A9: ARPU per host / month (Month 12) | B9: =Projection!O14 | E9: Affiliate | F9: =Projection!I15 | G9: =F9/$F$12
A10: ARPU per listener / month (Month 12) | B10: =Projection!P14 | E10: Done-for-you setup | F10: =Projection!J15 | G10: =F10/$F$12
E11: VRChat event packages | F11: =Projection!K15 | G11: =F11/$F$12
E12: Total | F12: =SUM(F5:F11) | G12: =SUM(G5:G11)
A15: Notes
A16: Drivers and pricing live on the Assumptions tab — edit the shaded cells to run scenarios.
A17: Licensing-light streams (host plans, done-for-you, white-label, affiliate, tips) are modeled first;
A18: listener subscriptions / ad-supported radio are excluded until music licensing is secured.
A19: Done-for-you and event packages are one-time (non-recurring) and excluded from MRR.
A20: Conservative MVP-stage assumptions; not a forecast — a sizing tool for prioritization.

Sheet Assumptions
A1: WavePalace — Revenue Model Assumptions
A2: Blue / shaded cells are inputs — change these to run scenarios.
A4: Audience & growth drivers
A5: Starting active hosts / curators (Month 1) | B5: 50 | C5: DJs, world owners, lounge curators with a channel
A6: Host base monthly growth | B6: 0.12 | C6: MoM growth in active hosts
A7: Starting monthly active listeners (Month 1) | B7: 2000 | C7: Web + VRChat listeners
A8: Listener base monthly growth | B8: 0.15 | C8: MoM growth in MAU
A9: Host / creator monetization
A10: Host Pro price ($/mo) | B10: 12 | C10: Branding, vanity URL, uploads, animated visuals, analytics
A11: Host Pro conversion (% of hosts) | B11: 0.08 | C11: Share of hosts on a paid Pro plan
A12: Featured placement price ($/mo) | B12: 25 | C12: Promoted slot in the directory
A13: Featured placement (% of hosts) | B13: 0.05 | C13: Share of hosts buying a featured slot
A14: Done-for-you channel setup ($ one-time) | B14: 150 | C14: Concierge: mux + host the customer's cleared media
A15: Done-for-you take rate (% of new hosts/mo) | B15: 0.1 | C15: New hosts each month buying setup
A16: VRChat event package ($ each) | B16: 40 | C16: Per-event curated set + reliable muxed link
A17: Event packages (% of hosts/mo) | B17: 0.04 | C17: Hosts running a paid event in the month
A18: Listener & passive monetization
A19: Tips: listeners tipping per month (% MAU) | B19: 0.015 | C19: Share of MAU leaving a tip
A20: Tips: average tip ($) | B20: 4 | C20: Gross tip amount
A21: Tips: platform take rate | B21: 0.15 | C21: WavePalace cut of each tip
A22: Affiliate: listeners clicking 'Listen elsewhere' (% MAU/mo) | B22: 0.3 | C22: Clickthrough on existing externalLinks
A23: Affiliate: click-to-signup conversion | B23: 0.04 | C23: Share of clicks that convert
A24: Affiliate: commission per conversion ($) | B24: 0.5 | C24: Referral payout from streaming partners
A25: B2B / white-label
A26: White-label client price ($/mo) | B26: 300 | C26: Embed player + mux pipeline for venues/communities
A27: White-label ramp (new clients / month) | B27: 0.3 | C27: Sales-led; ~1 client every ~3 months

Sheet Projection
A1: WavePalace — 12-Month Revenue Projection
A2: Month | B2: Active Hosts | C2: Active Listeners | D2: Paying Hosts | E2: Host Pro ($/mo) | F2: Featured ($/mo) | G2: White-label ($/mo) | H2: Tips net ($/mo) | I2: Affiliate ($/mo) | J2: Done-for-you ($/mo) | K2: Events ($/mo) | L2: Total Rev ($/mo) | M2: Cumulative ($) | N2: MRR ($/mo) | O2: ARPU/host ($/mo) | P2: ARPU/listener ($/mo)
A3: 1 | B3: =Assumptions!$B$5 | C3: =Assumptions!$B$7 | D3: =B3*Assumptions!$B$11 | E3: =D3*Assumptions!$B$10 | F3: =B3*Assumptions!$B$13*Assumptions!$B$12 | G3: =ROUND(A3*Assumptions!$B$27,0)*Assumptions!$B$26 | H3: =C3*Assumptions!$B$19*Assumptions!$B$20*Assumptions!$B$21 | I3: =C3*Assumptions!$B$22*Assumptions!$B$23*Assumptions!$B$24 | J3: =B3*Assumptions!$B$15*Assumptions!$B$14 | K3: =B3*Assumptions!$B$17*Assumptions!$B$16 | L3: =SUM(E3:K3) | M3: =L3 | N3: =E3+F3+G3+H3+I3 | O3: =L3/B3 | P3: =L3/C3
A4: 2 | B4: =B3*(1+Assumptions!$B$6) | C4: =C3*(1+Assumptions!$B$8) | D4: =B4*Assumptions!$B$11 | E4: =D4*Assumptions!$B$10 | F4: =B4*Assumptions!$B$13*Assumptions!$B$12 | G4: =ROUND(A4*Assumptions!$B$27,0)*Assumptions!$B$26 | H4: =C4*Assumptions!$B$19*Assumptions!$B$20*Assumptions!$B$21 | I4: =C4*Assumptions!$B$22*Assumptions!$B$23*Assumptions!$B$24 | J4: =(B4-B3)*Assumptions!$B$15*Assumptions!$B$14 | K4: =B4*Assumptions!$B$17*Assumptions!$B$16 | L4: =SUM(E4:K4) | M4: =M3+L4 | N4: =E4+F4+G4+H4+I4 | O4: =L4/B4 | P4: =L4/C4
A5: 3 | B5: =B4*(1+Assumptions!$B$6) | C5: =C4*(1+Assumptions!$B$8) | D5: =B5*Assumptions!$B$11 | E5: =D5*Assumptions!$B$10 | F5: =B5*Assumptions!$B$13*Assumptions!$B$12 | G5: =ROUND(A5*Assumptions!$B$27,0)*Assumptions!$B$26 | H5: =C5*Assumptions!$B$19*Assumptions!$B$20*Assumptions!$B$21 | I5: =C5*Assumptions!$B$22*Assumptions!$B$23*Assumptions!$B$24 | J5: =(B5-B4)*Assumptions!$B$15*Assumptions!$B$14 | K5: =B5*Assumptions!$B$17*Assumptions!$B$16 | L5: =SUM(E5:K5) | M5: =M4+L5 | N5: =E5+F5+G5+H5+I5 | O5: =L5/B5 | P5: =L5/C5
A6: 4 | B6: =B5*(1+Assumptions!$B$6) | C6: =C5*(1+Assumptions!$B$8) | D6: =B6*Assumptions!$B$11 | E6: =D6*Assumptions!$B$10 | F6: =B6*Assumptions!$B$13*Assumptions!$B$12 | G6: =ROUND(A6*Assumptions!$B$27,0)*Assumptions!$B$26 | H6: =C6*Assumptions!$B$19*Assumptions!$B$20*Assumptions!$B$21 | I6: =C6*Assumptions!$B$22*Assumptions!$B$23*Assumptions!$B$24 | J6: =(B6-B5)*Assumptions!$B$15*Assumptions!$B$14 | K6: =B6*Assumptions!$B$17*Assumptions!$B$16 | L6: =SUM(E6:K6) | M6: =M5+L6 | N6: =E6+F6+G6+H6+I6 | O6: =L6/B6 | P6: =L6/C6
A7: 5 | B7: =B6*(1+Assumptions!$B$6) | C7: =C6*(1+Assumptions!$B$8) | D7: =B7*Assumptions!$B$11 | E7: =D7*Assumptions!$B$10 | F7: =B7*Assumptions!$B$13*Assumptions!$B$12 | G7: =ROUND(A7*Assumptions!$B$27,0)*Assumptions!$B$26 | H7: =C7*Assumptions!$B$19*Assumptions!$B$20*Assumptions!$B$21 | I7: =C7*Assumptions!$B$22*Assumptions!$B$23*Assumptions!$B$24 | J7: =(B7-B6)*Assumptions!$B$15*Assumptions!$B$14 | K7: =B7*Assumptions!$B$17*Assumptions!$B$16 | L7: =SUM(E7:K7) | M7: =M6+L7 | N7: =E7+F7+G7+H7+I7 | O7: =L7/B7 | P7: =L7/C7
A8: 6 | B8: =B7*(1+Assumptions!$B$6) | C8: =C7*(1+Assumptions!$B$8) | D8: =B8*Assumptions!$B$11 | E8: =D8*Assumptions!$B$10 | F8: =B8*Assumptions!$B$13*Assumptions!$B$12 | G8: =ROUND(A8*Assumptions!$B$27,0)*Assumptions!$B$26 | H8: =C8*Assumptions!$B$19*Assumptions!$B$20*Assumptions!$B$21 | I8: =C8*Assumptions!$B$22*Assumptions!$B$23*Assumptions!$B$24 | J8: =(B8-B7)*Assumptions!$B$15*Assumptions!$B$14 | K8: =B8*Assumptions!$B$17*Assumptions!$B$16 | L8: =SUM(E8:K8) | M8: =M7+L8 | N8: =E8+F8+G8+H8+I8 | O8: =L8/B8 | P8: =L8/C8
A9: 7 | B9: =B8*(1+Assumptions!$B$6) | C9: =C8*(1+Assumptions!$B$8) | D9: =B9*Assumptions!$B$11 | E9: =D9*Assumptions!$B$10 | F9: =B9*Assumptions!$B$13*Assumptions!$B$12 | G9: =ROUND(A9*Assumptions!$B$27,0)*Assumptions!$B$26 | H9: =C9*Assumptions!$B$19*Assumptions!$B$20*Assumptions!$B$21 | I9: =C9*Assumptions!$B$22*Assumptions!$B$23*Assumptions!$B$24 | J9: =(B9-B8)*Assumptions!$B$15*Assumptions!$B$14 | K9: =B9*Assumptions!$B$17*Assumptions!$B$16 | L9: =SUM(E9:K9) | M9: =M8+L9 | N9: =E9+F9+G9+H9+I9 | O9: =L9/B9 | P9: =L9/C9
A10: 8 | B10: =B9*(1+Assumptions!$B$6) | C10: =C9*(1+Assumptions!$B$8) | D10: =B10*Assumptions!$B$11 | E10: =D10*Assumptions!$B$10 | F10: =B10*Assumptions!$B$13*Assumptions!$B$12 | G10: =ROUND(A10*Assumptions!$B$27,0)*Assumptions!$B$26 | H10: =C10*Assumptions!$B$19*Assumptions!$B$20*Assumptions!$B$21 | I10: =C10*Assumptions!$B$22*Assumptions!$B$23*Assumptions!$B$24 | J10: =(B10-B9)*Assumptions!$B$15*Assumptions!$B$14 | K10: =B10*Assumptions!$B$17*Assumptions!$B$16 | L10: =SUM(E10:K10) | M10: =M9+L10 | N10: =E10+F10+G10+H10+I10 | O10: =L10/B10 | P10: =L10/C10
A11: 9 | B11: =B10*(1+Assumptions!$B$6) | C11: =C10*(1+Assumptions!$B$8) | D11: =B11*Assumptions!$B$11 | E11: =D11*Assumptions!$B$10 | F11: =B11*Assumptions!$B$13*Assumptions!$B$12 | G11: =ROUND(A11*Assumptions!$B$27,0)*Assumptions!$B$26 | H11: =C11*Assumptions!$B$19*Assumptions!$B$20*Assumptions!$B$21 | I11: =C11*Assumptions!$B$22*Assumptions!$B$23*Assumptions!$B$24 | J11: =(B11-B10)*Assumptions!$B$15*Assumptions!$B$14 | K11: =B11*Assumptions!$B$17*Assumptions!$B$16 | L11: =SUM(E11:K11) | M11: =M10+L11 | N11: =E11+F11+G11+H11+I11 | O11: =L11/B11 | P11: =L11/C11
A12: 10 | B12: =B11*(1+Assumptions!$B$6) | C12: =C11*(1+Assumptions!$B$8) | D12: =B12*Assumptions!$B$11 | E12: =D12*Assumptions!$B$10 | F12: =B12*Assumptions!$B$13*Assumptions!$B$12 | G12: =ROUND(A12*Assumptions!$B$27,0)*Assumptions!$B$26 | H12: =C12*Assumptions!$B$19*Assumptions!$B$20*Assumptions!$B$21 | I12: =C12*Assumptions!$B$22*Assumptions!$B$23*Assumptions!$B$24 | J12: =(B12-B11)*Assumptions!$B$15*Assumptions!$B$14 | K12: =B12*Assumptions!$B$17*Assumptions!$B$16 | L12: =SUM(E12:K12) | M12: =M11+L12 | N12: =E12+F12+G12+H12+I12 | O12: =L12/B12 | P12: =L12/C12
A13: 11 | B13: =B12*(1+Assumptions!$B$6) | C13: =C12*(1+Assumptions!$B$8) | D13: =B13*Assumptions!$B$11 | E13: =D13*Assumptions!$B$10 | F13: =B13*Assumptions!$B$13*Assumptions!$B$12 | G13: =ROUND(A13*Assumptions!$B$27,0)*Assumptions!$B$26 | H13: =C13*Assumptions!$B$19*Assumptions!$B$20*Assumptions!$B$21 | I13: =C13*Assumptions!$B$22*Assumptions!$B$23*Assumptions!$B$24 | J13: =(B13-B12)*Assumptions!$B$15*Assumptions!$B$14 | K13: =B13*Assumptions!$B$17*Assumptions!$B$16 | L13: =SUM(E13:K13) | M13: =M12+L13 | N13: =E13+F13+G13+H13+I13 | O13: =L13/B13 | P13: =L13/C13
A14: 12 | B14: =B13*(1+Assumptions!$B$6) | C14: =C13*(1+Assumptions!$B$8) | D14: =B14*Assumptions!$B$11 | E14: =D14*Assumptions!$B$10 | F14: =B14*Assumptions!$B$13*Assumptions!$B$12 | G14: =ROUND(A14*Assumptions!$B$27,0)*Assumptions!$B$26 | H14: =C14*Assumptions!$B$19*Assumptions!$B$20*Assumptions!$B$21 | I14: =C14*Assumptions!$B$22*Assumptions!$B$23*Assumptions!$B$24 | J14: =(B14-B13)*Assumptions!$B$15*Assumptions!$B$14 | K14: =B14*Assumptions!$B$17*Assumptions!$B$16 | L14: =SUM(E14:K14) | M14: =M13+L14 | N14: =E14+F14+G14+H14+I14 | O14: =L14/B14 | P14: =L14/C14
A15: Year 1 | E15: =SUM(E3:E14) | F15: =SUM(F3:F14) | G15: =SUM(G3:G14) | H15: =SUM(H3:H14) | I15: =SUM(I3:I14) | J15: =SUM(J3:J14) | K15: =SUM(K3:K14) | L15: =SUM(L3:L14) | M15: =M14
